{
	"info": {
		"_postman_id": "b24050c9-6bc2-404e-8336-04135f9df492",
		"name": "SSO",
		"schema": "https://schema.getpostman.com/json/collection/v2.1.0/collection.json"
	},
	"item": [
		{
			"name": "Main Requests",
			"item": [
				{
					"name": "Authentification",
					"item": [
						{
							"name": "Login Authorize",
							"request": {
								"method": "POST",
								"header": [
									{
										"key": "Content-Type",
										"name": "Content-Type",
										"value": "application/json",
										"type": "text"
									}
								],
								"body": {
									"mode": "raw",
									"raw": "\t{\n\t\t\"Email\":\"spiderman@gmail.com\",\"Password\":\"uncleBen\"\n\t}"
								},
								"url": {
									"raw": "{{host}}/login-authorize",
									"host": [
										"{{host}}"
									],
									"path": [
										"login-authorize"
									]
								}
							},
							"response": []
						},
						{
							"name": "Token Check",
							"request": {
								"auth": {
									"type": "bearer",
									"bearer": [
										{
											"key": "token",
											"value": "{{token}}",
											"type": "string"
										}
									]
								},
								"method": "POST",
								"header": [],
								"url": {
									"raw": "{{host}}/check-token",
									"host": [
										"{{host}}"
									],
									"path": [
										"check-token"
									]
								}
							},
							"response": []
						},
						{
							"name": "Refresh Token",
							"request": {
								"auth": {
									"type": "bearer",
									"bearer": [
										{
											"key": "token",
											"value": "{{token}}",
											"type": "string"
										}
									]
								},
								"method": "POST",
								"header": [],
								"url": {
									"raw": "{{host}}/refresh-token",
									"host": [
										"{{host}}"
									],
									"path": [
										"refresh-token"
									]
								}
							},
							"response": []
						}
					],
					"protocolProfileBehavior": {},
					"_postman_isSubFolder": true
				},
				{
					"name": "GetStuff",
					"item": [
						{
							"name": "Get User Info",
							"request": {
								"auth": {
									"type": "bearer",
									"bearer": [
										{
											"key": "token",
											"value": "{{token}}",
											"type": "string"
										}
									]
								},
								"method": "POST",
								"header": [],
								"url": {
									"raw": "{{host}}/get-user-info/1",
									"host": [
										"{{host}}"
									],
									"path": [
										"get-user-info",
										"1"
									]
								}
							},
							"response": []
						},
						{
							"name": "Get My User Info",
							"request": {
								"auth": {
									"type": "bearer",
									"bearer": [
										{
											"key": "token",
											"value": "{{token}}",
											"type": "string"
										}
									]
								},
								"method": "POST",
								"header": [],
								"url": {
									"raw": "{{host}}/my-user-info",
									"host": [
										"{{host}}"
									],
									"path": [
										"my-user-info"
									]
								}
							},
							"response": []
						},
						{
							"name": "Have Permission",
							"request": {
								"auth": {
									"type": "bearer",
									"bearer": [
										{
											"key": "token",
											"value": "{{token}}",
											"type": "string"
										}
									]
								},
								"method": "POST",
								"header": [
									{
										"key": "Content-Type",
										"name": "Content-Type",
										"value": "application/json",
										"type": "text"
									}
								],
								"body": {
									"mode": "raw",
									"raw": "[\n{\"Slug\":\"edit-plan\",\"Table\":\"common\"},\n{\"Slug\":\"false-permission\",\"Table\":\"common\"}\n]"
								},
								"url": {
									"raw": "{{host}}/allowed-permissions",
									"host": [
										"{{host}}"
									],
									"path": [
										"allowed-permissions"
									]
								}
							},
							"response": []
						}
					],
					"protocolProfileBehavior": {},
					"_postman_isSubFolder": true
				},
				{
					"name": "SetStuff",
					"item": [
						{
							"name": "SetPermissionsToRole",
							"request": {
								"auth": {
									"type": "bearer",
									"bearer": [
										{
											"key": "token",
											"value": "{{token}}",
											"type": "string"
										}
									]
								},
								"method": "POST",
								"header": [
									{
										"key": "Content-Type",
										"name": "Content-Type",
										"type": "text",
										"value": "application/json"
									}
								],
								"body": {
									"mode": "raw",
									"raw": "{\r\n\t\"PermissionsId\":[1,2,3,4,5]\r\n}"
								},
								"url": {
									"raw": "{{host}}/set-permissions-to-role/2",
									"host": [
										"{{host}}"
									],
									"path": [
										"set-permissions-to-role",
										"2"
									]
								}
							},
							"response": []
						},
						{
							"name": "Set Roles To User",
							"request": {
								"auth": {
									"type": "bearer",
									"bearer": [
										{
											"key": "token",
											"value": "{{token}}",
											"type": "string"
										}
									]
								},
								"method": "POST",
								"header": [
									{
										"key": "Content-Type",
										"name": "Content-Type",
										"type": "text",
										"value": "application/json"
									}
								],
								"body": {
									"mode": "raw",
									"raw": "{\n\t\"RolesId\":[ 1,2 ]\n}"
								},
								"url": {
									"raw": "{{host}}/set-roles-to-user/2",
									"host": [
										"{{host}}"
									],
									"path": [
										"set-roles-to-user",
										"2"
									]
								}
							},
							"response": []
						}
					],
					"protocolProfileBehavior": {},
					"_postman_isSubFolder": true
				}
			],
			"protocolProfileBehavior": {}
		},
		{
			"name": "Invites_CRUD",
			"item": [
				{
					"name": "invite",
					"request": {
						"auth": {
							"type": "bearer",
							"bearer": [
								{
									"key": "token",
									"value": "{{token}}",
									"type": "string"
								}
							]
						},
						"method": "POST",
						"header": [
							{
								"key": "Content-Type",
								"name": "Content-Type",
								"type": "text",
								"value": "application/json"
							}
						],
						"body": {
							"mode": "raw",
							"raw": "{\r\n    \"Email\": \"some@email\",\r\n    \"CompanyId\":1,\r\n    \"Token\":\"token_example\"\r\n}"
						},
						"url": {
							"raw": "{{host}}/invite",
							"host": [
								"{{host}}"
							],
							"path": [
								"invite"
							]
						}
					},
					"response": []
				},
				{
					"name": "invite/{id}",
					"request": {
						"auth": {
							"type": "bearer",
							"bearer": [
								{
									"key": "token",
									"value": "{{token}}",
									"type": "string"
								}
							]
						},
						"method": "PUT",
						"header": [
							{
								"key": "Content-Type",
								"name": "Content-Type",
								"type": "text",
								"value": "application/json"
							}
						],
						"body": {
							"mode": "raw",
							"raw": "{\r\n\t\"Id\":3,\r\n    \"Email\": \"some@email\",\r\n    \"CompanyId\":1,\r\n    \"Token\":\"token_example\"\r\n}"
						},
						"url": {
							"raw": "{{host}}/invite/3",
							"host": [
								"{{host}}"
							],
							"path": [
								"invite",
								"3"
							]
						}
					},
					"response": []
				},
				{
					"name": "invite/{id}",
					"request": {
						"auth": {
							"type": "bearer",
							"bearer": [
								{
									"key": "token",
									"value": "{{token}}",
									"type": "string"
								}
							]
						},
						"method": "DELETE",
						"header": [
							{
								"key": "Content-Type",
								"name": "Content-Type",
								"type": "text",
								"value": "application/json"
							}
						],
						"body": {
							"mode": "raw",
							"raw": ""
						},
						"url": {
							"raw": "{{host}}/invite/3",
							"host": [
								"{{host}}"
							],
							"path": [
								"invite",
								"3"
							]
						}
					},
					"response": []
				},
				{
					"name": "invite",
					"protocolProfileBehavior": {
						"disableBodyPruning": true
					},
					"request": {
						"auth": {
							"type": "bearer",
							"bearer": [
								{
									"key": "token",
									"value": "{{token}}",
									"type": "string"
								}
							]
						},
						"method": "GET",
						"header": [
							{
								"key": "Content-Type",
								"name": "Content-Type",
								"type": "text",
								"value": "application/json"
							}
						],
						"body": {
							"mode": "raw",
							"raw": ""
						},
						"url": {
							"raw": "{{host}}/invite",
							"host": [
								"{{host}}"
							],
							"path": [
								"invite"
							]
						}
					},
					"response": []
				},
				{
					"name": "invite/{id}",
					"protocolProfileBehavior": {
						"disableBodyPruning": true
					},
					"request": {
						"auth": {
							"type": "bearer",
							"bearer": [
								{
									"key": "token",
									"value": "{{token}}",
									"type": "string"
								}
							]
						},
						"method": "GET",
						"header": [],
						"body": {
							"mode": "raw",
							"raw": ""
						},
						"url": {
							"raw": "{{host}}/invite/1",
							"host": [
								"{{host}}"
							],
							"path": [
								"invite",
								"1"
							]
						}
					},
					"response": []
				},
				{
					"name": "invite/company/{id}",
					"protocolProfileBehavior": {
						"disableBodyPruning": true
					},
					"request": {
						"auth": {
							"type": "bearer",
							"bearer": [
								{
									"key": "token",
									"value": "{{token}}",
									"type": "string"
								}
							]
						},
						"method": "GET",
						"header": [],
						"body": {
							"mode": "raw",
							"raw": ""
						},
						"url": {
							"raw": "{{host}}/invite/company/1",
							"host": [
								"{{host}}"
							],
							"path": [
								"invite",
								"company",
								"1"
							]
						}
					},
					"response": []
				}
			],
			"protocolProfileBehavior": {}
		},
		{
			"name": "InviteRoles_CRUD",
			"item": [
				{
					"name": "invite-roles",
					"request": {
						"auth": {
							"type": "bearer",
							"bearer": [
								{
									"key": "token",
									"value": "{{token}}",
									"type": "string"
								}
							]
						},
						"method": "POST",
						"header": [
							{
								"key": "Content-Type",
								"name": "Content-Type",
								"type": "text",
								"value": "application/json"
							}
						],
						"body": {
							"mode": "raw",
							"raw": "{\r\n    \"Email\": \"some@email\",\r\n    \"CompanyId\":1,\r\n    \"Token\":\"token_example\"\r\n}"
						},
						"url": {
							"raw": "{{host}}/invite-roles",
							"host": [
								"{{host}}"
							],
							"path": [
								"invite-roles"
							]
						}
					},
					"response": []
				},
				{
					"name": "invite-roles/{id}",
					"request": {
						"auth": {
							"type": "bearer",
							"bearer": [
								{
									"key": "token",
									"value": "{{token}}",
									"type": "string"
								}
							]
						},
						"method": "PUT",
						"header": [
							{
								"key": "Content-Type",
								"name": "Content-Type",
								"type": "text",
								"value": "application/json"
							}
						],
						"body": {
							"mode": "raw",
							"raw": "{\r\n\t\"Id\":3,\r\n    \"RoleId\": 1,\r\n    \"InviteId\":1\r\n}"
						},
						"url": {
							"raw": "{{host}}/invite-roles/3",
							"host": [
								"{{host}}"
							],
							"path": [
								"invite-roles",
								"3"
							]
						}
					},
					"response": []
				},
				{
					"name": "invite-roles/{id}",
					"request": {
						"auth": {
							"type": "bearer",
							"bearer": [
								{
									"key": "token",
									"value": "{{token}}",
									"type": "string"
								}
							]
						},
						"method": "DELETE",
						"header": [
							{
								"key": "Content-Type",
								"name": "Content-Type",
								"type": "text",
								"value": "application/json"
							}
						],
						"body": {
							"mode": "raw",
							"raw": ""
						},
						"url": {
							"raw": "{{host}}/invite-roles/3",
							"host": [
								"{{host}}"
							],
							"path": [
								"invite-roles",
								"3"
							]
						}
					},
					"response": []
				},
				{
					"name": "invite-roles",
					"protocolProfileBehavior": {
						"disableBodyPruning": true
					},
					"request": {
						"auth": {
							"type": "bearer",
							"bearer": [
								{
									"key": "token",
									"value": "{{token}}",
									"type": "string"
								}
							]
						},
						"method": "GET",
						"header": [
							{
								"key": "Content-Type",
								"name": "Content-Type",
								"type": "text",
								"value": "application/json"
							}
						],
						"body": {
							"mode": "raw",
							"raw": ""
						},
						"url": {
							"raw": "{{host}}/invite-roles",
							"host": [
								"{{host}}"
							],
							"path": [
								"invite-roles"
							]
						}
					},
					"response": []
				},
				{
					"name": "invite-roles/{id}",
					"protocolProfileBehavior": {
						"disableBodyPruning": true
					},
					"request": {
						"auth": {
							"type": "bearer",
							"bearer": [
								{
									"key": "token",
									"value": "{{token}}",
									"type": "string"
								}
							]
						},
						"method": "GET",
						"header": [],
						"body": {
							"mode": "raw",
							"raw": ""
						},
						"url": {
							"raw": "{{host}}/invite-roles/1",
							"host": [
								"{{host}}"
							],
							"path": [
								"invite-roles",
								"1"
							]
						}
					},
					"response": []
				},
				{
					"name": "invite-roles/role/{id}",
					"protocolProfileBehavior": {
						"disableBodyPruning": true
					},
					"request": {
						"auth": {
							"type": "bearer",
							"bearer": [
								{
									"key": "token",
									"value": "{{token}}",
									"type": "string"
								}
							]
						},
						"method": "GET",
						"header": [],
						"body": {
							"mode": "raw",
							"raw": ""
						},
						"url": {
							"raw": "{{host}}/invite-roles/role/1",
							"host": [
								"{{host}}"
							],
							"path": [
								"invite-roles",
								"role",
								"1"
							]
						}
					},
					"response": []
				},
				{
					"name": "invite-roles/invite/{id}",
					"protocolProfileBehavior": {
						"disableBodyPruning": true
					},
					"request": {
						"auth": {
							"type": "bearer",
							"bearer": [
								{
									"key": "token",
									"value": "{{token}}",
									"type": "string"
								}
							]
						},
						"method": "GET",
						"header": [],
						"body": {
							"mode": "raw",
							"raw": ""
						},
						"url": {
							"raw": "{{host}}/invite-roles/invite/1",
							"host": [
								"{{host}}"
							],
							"path": [
								"invite-roles",
								"invite",
								"1"
							]
						}
					},
					"response": []
				}
			],
			"protocolProfileBehavior": {}
		},
		{
			"name": "UserParameters_CRUD",
			"item": [
				{
					"name": "user_params/add",
					"request": {
						"auth": {
							"type": "bearer",
							"bearer": [
								{
									"key": "token",
									"value": "{{token}}",
									"type": "string"
								}
							]
						},
						"method": "POST",
						"header": [
							{
								"key": "Content-Type",
								"name": "Content-Type",
								"type": "text",
								"value": "application/json"
							}
						],
						"body": {
							"mode": "raw",
							"raw": "{\r\n    \"UserId\": 1,\r\n    \"Value\":\"example@mail\",\r\n    \"Key\":\"email\"\r\n}"
						},
						"url": {
							"raw": "{{host}}/user-params",
							"host": [
								"{{host}}"
							],
							"path": [
								"user-params"
							]
						}
					},
					"response": []
				},
				{
					"name": "user_params/update",
					"request": {
						"auth": {
							"type": "bearer",
							"bearer": [
								{
									"key": "token",
									"value": "{{token}}",
									"type": "string"
								}
							]
						},
						"method": "PUT",
						"header": [
							{
								"key": "Content-Type",
								"name": "Content-Type",
								"type": "text",
								"value": "application/json"
							}
						],
						"body": {
							"mode": "raw",
							"raw": "{\r\n\t\"Id\":4,\r\n    \"UserId\": 2,\r\n    \"Key\":\"updated_email\",\r\n    \"Value\":\"updated_example@mail\"\r\n}"
						},
						"url": {
							"raw": "{{host}}/user-params/4",
							"host": [
								"{{host}}"
							],
							"path": [
								"user-params",
								"4"
							]
						}
					},
					"response": []
				},
				{
					"name": "user_params/delete/{id}",
					"request": {
						"auth": {
							"type": "bearer",
							"bearer": [
								{
									"key": "token",
									"value": "{{token}}",
									"type": "string"
								}
							]
						},
						"method": "DELETE",
						"header": [
							{
								"key": "Content-Type",
								"name": "Content-Type",
								"type": "text",
								"value": "application/json",
								"disabled": true
							}
						],
						"url": {
							"raw": "{{host}}/user-params/4",
							"host": [
								"{{host}}"
							],
							"path": [
								"user-params",
								"4"
							]
						}
					},
					"response": []
				},
				{
					"name": "get list",
					"request": {
						"auth": {
							"type": "bearer",
							"bearer": [
								{
									"key": "token",
									"value": "{{token}}",
									"type": "string"
								}
							]
						},
						"method": "GET",
						"header": [
							{
								"key": "Content-Type",
								"name": "Content-Type",
								"type": "text",
								"value": "application/json",
								"disabled": true
							}
						],
						"url": {
							"raw": "{{host}}/user-params",
							"host": [
								"{{host}}"
							],
							"path": [
								"user-params"
							]
						}
					},
					"response": []
				},
				{
					"name": "get item",
					"protocolProfileBehavior": {
						"disableBodyPruning": true
					},
					"request": {
						"auth": {
							"type": "bearer",
							"bearer": [
								{
									"key": "token",
									"value": "{{token}}",
									"type": "string"
								}
							]
						},
						"method": "GET",
						"header": [],
						"body": {
							"mode": "raw",
							"raw": ""
						},
						"url": {
							"raw": "{{host}}/user-params/1",
							"host": [
								"{{host}}"
							],
							"path": [
								"user-params",
								"1"
							]
						}
					},
					"response": []
				},
				{
					"name": "user_params/getbyuser/{id}",
					"request": {
						"auth": {
							"type": "bearer",
							"bearer": [
								{
									"key": "token",
									"value": "{{token}}",
									"type": "string"
								}
							]
						},
						"method": "GET",
						"header": [],
						"url": {
							"raw": "{{host}}/user-params/user/1",
							"host": [
								"{{host}}"
							],
							"path": [
								"user-params",
								"user",
								"1"
							]
						}
					},
					"response": []
				}
			],
			"protocolProfileBehavior": {}
		},
		{
			"name": "User_CRUD",
			"item": [
				{
					"name": "users/add",
					"request": {
						"auth": {
							"type": "bearer",
							"bearer": [
								{
									"key": "token",
									"value": "{{token}}",
									"type": "string"
								}
							]
						},
						"method": "POST",
						"header": [
							{
								"key": "Content-Type",
								"name": "Content-Type",
								"value": "application/json",
								"type": "text"
							}
						],
						"body": {
							"mode": "raw",
							"raw": "{\r\n\r\n    \"Name\": \"Shkrek\",\r\n    \"FirstName\":\"Bob\",\r\n    \"LastName\":\"Wise\",\r\n    \"Email\":\"swamp@gmail.com\",\r\n    \"Password\":\"zhopa\",\r\n    \"PhoneNumber\":\"+3232323\",\r\n    \"CompanyId\":1\r\n}"
						},
						"url": {
							"raw": "{{host}}/users",
							"host": [
								"{{host}}"
							],
							"path": [
								"users"
							]
						}
					},
					"response": []
				},
				{
					"name": "users/update",
					"request": {
						"auth": {
							"type": "bearer",
							"bearer": [
								{
									"key": "token",
									"value": "{{token}}",
									"type": "string"
								}
							]
						},
						"method": "PUT",
						"header": [
							{
								"key": "Content-Type",
								"name": "Content-Type",
								"value": "application/json",
								"type": "text"
							}
						],
						"body": {
							"mode": "raw",
							"raw": "{\r\n    \"Id\": 3,\r\n    \"FirstName\":\"NotBOB\",\r\n    \"LastName\":\"Wise\",\r\n    \"Email\":\"SHREK@gmail.com\",\r\n    \"Password\":\"$2b$11$o2Ii5lNeYxCCzXm6nw5Lw..k4dopzVztVuzlEBPe4nBQmNQ0SF.RO\",\r\n    \"PhoneNumber\":\"+3232323\",\r\n    \"CompanyId\":1\r\n}"
						},
						"url": {
							"raw": "{{host}}/users/3",
							"host": [
								"{{host}}"
							],
							"path": [
								"users",
								"3"
							]
						}
					},
					"response": []
				},
				{
					"name": "users/delete/{id}",
					"request": {
						"auth": {
							"type": "bearer",
							"bearer": [
								{
									"key": "token",
									"value": "{{token}}",
									"type": "string"
								}
							]
						},
						"method": "DELETE",
						"header": [
							{
								"key": "Content-Type",
								"name": "Content-Type",
								"type": "text",
								"value": "application/json"
							}
						],
						"body": {
							"mode": "raw",
							"raw": ""
						},
						"url": {
							"raw": "{{host}}/users/3",
							"host": [
								"{{host}}"
							],
							"path": [
								"users",
								"3"
							]
						}
					},
					"response": []
				},
				{
					"name": "users/getlist",
					"protocolProfileBehavior": {
						"disableBodyPruning": true
					},
					"request": {
						"auth": {
							"type": "bearer",
							"bearer": [
								{
									"key": "token",
									"value": "{{token}}",
									"type": "string"
								}
							]
						},
						"method": "GET",
						"header": [
							{
								"key": "Content-Type",
								"name": "Content-Type",
								"value": "application/json",
								"type": "text"
							}
						],
						"body": {
							"mode": "raw",
							"raw": ""
						},
						"url": {
							"raw": "{{host}}/users",
							"host": [
								"{{host}}"
							],
							"path": [
								"users"
							]
						}
					},
					"response": []
				},
				{
					"name": "users/getitem/{id}",
					"protocolProfileBehavior": {
						"disableBodyPruning": true
					},
					"request": {
						"auth": {
							"type": "bearer",
							"bearer": [
								{
									"key": "token",
									"value": "{{token}}",
									"type": "string"
								}
							]
						},
						"method": "GET",
						"header": [],
						"body": {
							"mode": "raw",
							"raw": ""
						},
						"url": {
							"raw": "{{host}}/users/1",
							"host": [
								"{{host}}"
							],
							"path": [
								"users",
								"1"
							]
						}
					},
					"response": []
				},
				{
					"name": "users/getbycompany/{id}",
					"request": {
						"auth": {
							"type": "bearer",
							"bearer": [
								{
									"key": "token",
									"value": "{{token}}",
									"type": "string"
								}
							]
						},
						"method": "GET",
						"header": [],
						"url": {
							"raw": "{{host}}/users/company/1",
							"host": [
								"{{host}}"
							],
							"path": [
								"users",
								"company",
								"1"
							]
						}
					},
					"response": []
				}
			],
			"protocolProfileBehavior": {}
		},
		{
			"name": "Company_CRUD",
			"item": [
				{
					"name": "company/add",
					"request": {
						"auth": {
							"type": "bearer",
							"bearer": [
								{
									"key": "token",
									"value": "{{token}}",
									"type": "string"
								}
							]
						},
						"method": "POST",
						"header": [
							{
								"key": "Content-Type",
								"name": "Content-Type",
								"type": "text",
								"value": "application/json"
							}
						],
						"body": {
							"mode": "raw",
							"raw": "{\r\n\r\n    \"CompanyName\": \"Example Company\",\r\n    \"Slug\":\"Example-Company\"\r\n}"
						},
						"url": {
							"raw": "{{host}}/company",
							"host": [
								"{{host}}"
							],
							"path": [
								"company"
							]
						}
					},
					"response": []
				},
				{
					"name": "company/update",
					"request": {
						"auth": {
							"type": "bearer",
							"bearer": [
								{
									"key": "token",
									"value": "{{token}}",
									"type": "string"
								}
							]
						},
						"method": "PUT",
						"header": [
							{
								"key": "Content-Type",
								"name": "Content-Type",
								"type": "text",
								"value": "application/json"
							}
						],
						"body": {
							"mode": "raw",
							"raw": "{\r\n\t\"Id\":3,\r\n    \"CompanyName\": \"Example FUCKUpdatedCompany\",\r\n    \"Slug\":\"Example-UpdatedCompany\"\r\n}"
						},
						"url": {
							"raw": "{{host}}/company/3",
							"host": [
								"{{host}}"
							],
							"path": [
								"company",
								"3"
							]
						}
					},
					"response": []
				},
				{
					"name": "company/delete/{id}",
					"request": {
						"auth": {
							"type": "bearer",
							"bearer": [
								{
									"key": "token",
									"value": "{{token}}",
									"type": "string"
								}
							]
						},
						"method": "DELETE",
						"header": [
							{
								"key": "Content-Type",
								"name": "Content-Type",
								"type": "text",
								"value": "application/json"
							}
						],
						"body": {
							"mode": "raw",
							"raw": ""
						},
						"url": {
							"raw": "{{host}}/company/3",
							"host": [
								"{{host}}"
							],
							"path": [
								"company",
								"3"
							]
						}
					},
					"response": []
				},
				{
					"name": "company/getlist",
					"protocolProfileBehavior": {
						"disableBodyPruning": true
					},
					"request": {
						"auth": {
							"type": "bearer",
							"bearer": [
								{
									"key": "token",
									"value": "{{token}}",
									"type": "string"
								}
							]
						},
						"method": "GET",
						"header": [
							{
								"key": "Content-Type",
								"name": "Content-Type",
								"type": "text",
								"value": "application/json"
							}
						],
						"body": {
							"mode": "raw",
							"raw": ""
						},
						"url": {
							"raw": "{{host}}/company",
							"host": [
								"{{host}}"
							],
							"path": [
								"company"
							]
						}
					},
					"response": []
				},
				{
					"name": "company/getitem/{id}",
					"protocolProfileBehavior": {
						"disableBodyPruning": true
					},
					"request": {
						"auth": {
							"type": "bearer",
							"bearer": [
								{
									"key": "token",
									"value": "{{token}}",
									"type": "string"
								}
							]
						},
						"method": "GET",
						"header": [],
						"body": {
							"mode": "raw",
							"raw": ""
						},
						"url": {
							"raw": "{{host}}/company/1",
							"host": [
								"{{host}}"
							],
							"path": [
								"company",
								"1"
							]
						}
					},
					"response": []
				}
			],
			"protocolProfileBehavior": {}
		},
		{
			"name": "CompanyAirports_CRUD",
			"item": [
				{
					"name": "company-airports",
					"request": {
						"auth": {
							"type": "bearer",
							"bearer": [
								{
									"key": "token",
									"value": "{{token}}",
									"type": "string"
								}
							]
						},
						"method": "POST",
						"header": [
							{
								"key": "Content-Type",
								"name": "Content-Type",
								"type": "text",
								"value": "application/json"
							}
						],
						"body": {
							"mode": "raw",
							"raw": "{\r\n    \"CompanyId\": 1,\r\n    \"AirportId\":2\r\n}"
						},
						"url": {
							"raw": "{{host}}/company-airports",
							"host": [
								"{{host}}"
							],
							"path": [
								"company-airports"
							]
						}
					},
					"response": []
				},
				{
					"name": "company-airports/{id}",
					"request": {
						"auth": {
							"type": "bearer",
							"bearer": [
								{
									"key": "token",
									"value": "{{token}}",
									"type": "string"
								}
							]
						},
						"method": "PUT",
						"header": [
							{
								"key": "Content-Type",
								"name": "Content-Type",
								"type": "text",
								"value": "application/json"
							}
						],
						"body": {
							"mode": "raw",
							"raw": "{\r\n\t\"Id\":3,\r\n    \"CompanyId\": 1,\r\n    \"AirportId\":3\r\n}"
						},
						"url": {
							"raw": "{{host}}/company-airports/3",
							"host": [
								"{{host}}"
							],
							"path": [
								"company-airports",
								"3"
							]
						}
					},
					"response": []
				},
				{
					"name": "company-airports/{id}",
					"request": {
						"auth": {
							"type": "bearer",
							"bearer": [
								{
									"key": "token",
									"value": "{{token}}",
									"type": "string"
								}
							]
						},
						"method": "DELETE",
						"header": [
							{
								"key": "Content-Type",
								"name": "Content-Type",
								"type": "text",
								"value": "application/json"
							}
						],
						"body": {
							"mode": "raw",
							"raw": ""
						},
						"url": {
							"raw": "{{host}}/company-airports/3",
							"host": [
								"{{host}}"
							],
							"path": [
								"company-airports",
								"3"
							]
						}
					},
					"response": []
				},
				{
					"name": "company-airports",
					"protocolProfileBehavior": {
						"disableBodyPruning": true
					},
					"request": {
						"auth": {
							"type": "bearer",
							"bearer": [
								{
									"key": "token",
									"value": "{{token}}",
									"type": "string"
								}
							]
						},
						"method": "GET",
						"header": [
							{
								"key": "Content-Type",
								"name": "Content-Type",
								"type": "text",
								"value": "application/json"
							}
						],
						"body": {
							"mode": "raw",
							"raw": ""
						},
						"url": {
							"raw": "{{host}}/company-airports",
							"host": [
								"{{host}}"
							],
							"path": [
								"company-airports"
							]
						}
					},
					"response": []
				},
				{
					"name": "company-airports/{id}",
					"protocolProfileBehavior": {
						"disableBodyPruning": true
					},
					"request": {
						"auth": {
							"type": "bearer",
							"bearer": [
								{
									"key": "token",
									"value": "{{token}}",
									"type": "string"
								}
							]
						},
						"method": "GET",
						"header": [],
						"body": {
							"mode": "raw",
							"raw": ""
						},
						"url": {
							"raw": "{{host}}/company-airports/1",
							"host": [
								"{{host}}"
							],
							"path": [
								"company-airports",
								"1"
							]
						}
					},
					"response": []
				},
				{
					"name": "company-airports/company/{id}",
					"protocolProfileBehavior": {
						"disableBodyPruning": true
					},
					"request": {
						"auth": {
							"type": "bearer",
							"bearer": [
								{
									"key": "token",
									"value": "{{token}}",
									"type": "string"
								}
							]
						},
						"method": "GET",
						"header": [],
						"body": {
							"mode": "raw",
							"raw": ""
						},
						"url": {
							"raw": "{{host}}/company-airports/company/1",
							"host": [
								"{{host}}"
							],
							"path": [
								"company-airports",
								"company",
								"1"
							]
						}
					},
					"response": []
				}
			],
			"protocolProfileBehavior": {}
		},
		{
			"name": "Permission_CRUD",
			"item": [
				{
					"name": "permission/add",
					"request": {
						"auth": {
							"type": "bearer",
							"bearer": [
								{
									"key": "token",
									"value": "{{token}}",
									"type": "string"
								}
							]
						},
						"method": "POST",
						"header": [
							{
								"key": "Content-Type",
								"name": "Content-Type",
								"type": "text",
								"value": "application/json"
							}
						],
						"body": {
							"mode": "raw",
							"raw": "{\r\n    \"Slug\": \"Example-Permission\",\r\n    \"Table\":\"test\"\r\n}"
						},
						"url": {
							"raw": "{{host}}/permission",
							"host": [
								"{{host}}"
							],
							"path": [
								"permission"
							]
						}
					},
					"response": []
				},
				{
					"name": "permission/update",
					"request": {
						"auth": {
							"type": "bearer",
							"bearer": [
								{
									"key": "token",
									"value": "{{token}}",
									"type": "string"
								}
							]
						},
						"method": "PUT",
						"header": [
							{
								"key": "Content-Type",
								"name": "Content-Type",
								"type": "text",
								"value": "application/json"
							}
						],
						"body": {
							"mode": "raw",
							"raw": "{\r\n\t\"Id\":107,\r\n    \"Slug\": \"Example-UpdatedPermission\",\r\n    \"Table\":\"test\"\r\n}"
						},
						"url": {
							"raw": "{{host}}/permission/107",
							"host": [
								"{{host}}"
							],
							"path": [
								"permission",
								"107"
							]
						}
					},
					"response": []
				},
				{
					"name": "permission/delete/{id}",
					"request": {
						"auth": {
							"type": "bearer",
							"bearer": [
								{
									"key": "token",
									"value": "{{token}}",
									"type": "string"
								}
							]
						},
						"method": "DELETE",
						"header": [
							{
								"key": "Content-Type",
								"name": "Content-Type",
								"type": "text",
								"value": "application/json"
							}
						],
						"body": {
							"mode": "raw",
							"raw": ""
						},
						"url": {
							"raw": "{{host}}/permission/107",
							"host": [
								"{{host}}"
							],
							"path": [
								"permission",
								"107"
							]
						}
					},
					"response": []
				},
				{
					"name": "permission/getlist",
					"protocolProfileBehavior": {
						"disableBodyPruning": true
					},
					"request": {
						"auth": {
							"type": "bearer",
							"bearer": [
								{
									"key": "token",
									"value": "{{token}}",
									"type": "string"
								}
							]
						},
						"method": "GET",
						"header": [
							{
								"key": "Content-Type",
								"name": "Content-Type",
								"type": "text",
								"value": "application/json"
							}
						],
						"body": {
							"mode": "raw",
							"raw": ""
						},
						"url": {
							"raw": "{{host}}/permission",
							"host": [
								"{{host}}"
							],
							"path": [
								"permission"
							]
						}
					},
					"response": []
				},
				{
					"name": "permission/getitem/{id}",
					"protocolProfileBehavior": {
						"disableBodyPruning": true
					},
					"request": {
						"auth": {
							"type": "bearer",
							"bearer": [
								{
									"key": "token",
									"value": "{{token}}",
									"type": "string"
								}
							]
						},
						"method": "GET",
						"header": [],
						"body": {
							"mode": "raw",
							"raw": ""
						},
						"url": {
							"raw": "{{host}}/permission/100",
							"host": [
								"{{host}}"
							],
							"path": [
								"permission",
								"100"
							]
						}
					},
					"response": []
				}
			],
			"protocolProfileBehavior": {}
		},
		{
			"name": "Role_CRUD",
			"item": [
				{
					"name": "role/add",
					"request": {
						"auth": {
							"type": "bearer",
							"bearer": [
								{
									"key": "token",
									"value": "{{token}}",
									"type": "string"
								}
							]
						},
						"method": "POST",
						"header": [
							{
								"key": "Content-Type",
								"name": "Content-Type",
								"type": "text",
								"value": "application/json"
							}
						],
						"body": {
							"mode": "raw",
							"raw": "{\r\n    \"Slug\": \"Example-Role\",\r\n    \"CompanyId\":1\r\n}"
						},
						"url": {
							"raw": "{{host}}/role",
							"host": [
								"{{host}}"
							],
							"path": [
								"role"
							]
						}
					},
					"response": []
				},
				{
					"name": "role/update",
					"request": {
						"auth": {
							"type": "bearer",
							"bearer": [
								{
									"key": "token",
									"value": "{{token}}",
									"type": "string"
								}
							]
						},
						"method": "PUT",
						"header": [
							{
								"key": "Content-Type",
								"name": "Content-Type",
								"type": "text",
								"value": "application/json"
							}
						],
						"body": {
							"mode": "raw",
							"raw": "{\r\n\t\"Id\":3,\r\n    \"Slug\": \"Example-Role\",\r\n    \"CompanyId\":2\r\n}"
						},
						"url": {
							"raw": "{{host}}/role/3",
							"host": [
								"{{host}}"
							],
							"path": [
								"role",
								"3"
							]
						}
					},
					"response": []
				},
				{
					"name": "role/delete/{id}",
					"request": {
						"auth": {
							"type": "bearer",
							"bearer": [
								{
									"key": "token",
									"value": "{{token}}",
									"type": "string"
								}
							]
						},
						"method": "DELETE",
						"header": [
							{
								"key": "Content-Type",
								"name": "Content-Type",
								"type": "text",
								"value": "application/json"
							}
						],
						"body": {
							"mode": "raw",
							"raw": ""
						},
						"url": {
							"raw": "{{host}}/role/3",
							"host": [
								"{{host}}"
							],
							"path": [
								"role",
								"3"
							]
						}
					},
					"response": []
				},
				{
					"name": "role/getlist",
					"protocolProfileBehavior": {
						"disableBodyPruning": true
					},
					"request": {
						"auth": {
							"type": "bearer",
							"bearer": [
								{
									"key": "token",
									"value": "{{token}}",
									"type": "string"
								}
							]
						},
						"method": "GET",
						"header": [
							{
								"key": "Content-Type",
								"name": "Content-Type",
								"type": "text",
								"value": "application/json"
							}
						],
						"body": {
							"mode": "raw",
							"raw": ""
						},
						"url": {
							"raw": "{{host}}/role",
							"host": [
								"{{host}}"
							],
							"path": [
								"role"
							]
						}
					},
					"response": []
				},
				{
					"name": "role/getitem/{id}",
					"protocolProfileBehavior": {
						"disableBodyPruning": true
					},
					"request": {
						"auth": {
							"type": "bearer",
							"bearer": [
								{
									"key": "token",
									"value": "{{token}}",
									"type": "string"
								}
							]
						},
						"method": "GET",
						"header": [],
						"body": {
							"mode": "raw",
							"raw": ""
						},
						"url": {
							"raw": "{{host}}/role/1",
							"host": [
								"{{host}}"
							],
							"path": [
								"role",
								"1"
							]
						}
					},
					"response": []
				},
				{
					"name": "role/getbycompany/{id}",
					"protocolProfileBehavior": {
						"disableBodyPruning": true
					},
					"request": {
						"auth": {
							"type": "bearer",
							"bearer": [
								{
									"key": "token",
									"value": "{{token}}",
									"type": "string"
								}
							]
						},
						"method": "GET",
						"header": [],
						"body": {
							"mode": "raw",
							"raw": ""
						},
						"url": {
							"raw": "{{host}}/role/company/1",
							"host": [
								"{{host}}"
							],
							"path": [
								"role",
								"company",
								"1"
							]
						}
					},
					"response": []
				}
			],
			"protocolProfileBehavior": {}
		},
		{
			"name": "UserRoles_CRUD",
			"item": [
				{
					"name": "user_role/getlist",
					"protocolProfileBehavior": {
						"disableBodyPruning": true
					},
					"request": {
						"auth": {
							"type": "bearer",
							"bearer": [
								{
									"key": "token",
									"value": "{{token}}",
									"type": "string"
								}
							]
						},
						"method": "GET",
						"header": [
							{
								"key": "Content-Type",
								"name": "Content-Type",
								"type": "text",
								"value": "application/json"
							}
						],
						"body": {
							"mode": "raw",
							"raw": ""
						},
						"url": {
							"raw": "{{host}}/user-role",
							"host": [
								"{{host}}"
							],
							"path": [
								"user-role"
							]
						}
					},
					"response": []
				},
				{
					"name": "user_role/getitem/{id}",
					"protocolProfileBehavior": {
						"disableBodyPruning": true
					},
					"request": {
						"auth": {
							"type": "bearer",
							"bearer": [
								{
									"key": "token",
									"value": "{{token}}",
									"type": "string"
								}
							]
						},
						"method": "GET",
						"header": [],
						"body": {
							"mode": "raw",
							"raw": ""
						},
						"url": {
							"raw": "{{host}}/user-role/1",
							"host": [
								"{{host}}"
							],
							"path": [
								"user-role",
								"1"
							]
						}
					},
					"response": []
				},
				{
					"name": "user_role/getbyrole/{id}",
					"protocolProfileBehavior": {
						"disableBodyPruning": true
					},
					"request": {
						"auth": {
							"type": "bearer",
							"bearer": [
								{
									"key": "token",
									"value": "{{token}}",
									"type": "string"
								}
							]
						},
						"method": "GET",
						"header": [],
						"body": {
							"mode": "raw",
							"raw": ""
						},
						"url": {
							"raw": "{{host}}/user-role/role/2",
							"host": [
								"{{host}}"
							],
							"path": [
								"user-role",
								"role",
								"2"
							]
						}
					},
					"response": []
				},
				{
					"name": "user_role/getbyuser/{id}",
					"protocolProfileBehavior": {
						"disableBodyPruning": true
					},
					"request": {
						"auth": {
							"type": "bearer",
							"bearer": [
								{
									"key": "token",
									"value": "{{token}}",
									"type": "string"
								}
							]
						},
						"method": "GET",
						"header": [],
						"body": {
							"mode": "raw",
							"raw": ""
						},
						"url": {
							"raw": "{{host}}/user-role/user/1",
							"host": [
								"{{host}}"
							],
							"path": [
								"user-role",
								"user",
								"1"
							]
						}
					},
					"response": []
				}
			],
			"protocolProfileBehavior": {}
		},
		{
			"name": "RolePermissions_CRUD",
			"item": [
				{
					"name": "role_permission/getlist",
					"protocolProfileBehavior": {
						"disableBodyPruning": true
					},
					"request": {
						"auth": {
							"type": "bearer",
							"bearer": [
								{
									"key": "token",
									"value": "{{token}}",
									"type": "string"
								}
							]
						},
						"method": "GET",
						"header": [
							{
								"key": "Content-Type",
								"name": "Content-Type",
								"type": "text",
								"value": "application/json"
							}
						],
						"body": {
							"mode": "raw",
							"raw": ""
						},
						"url": {
							"raw": "{{host}}/role-permission",
							"host": [
								"{{host}}"
							],
							"path": [
								"role-permission"
							]
						}
					},
					"response": []
				},
				{
					"name": "role_permission/getitem/{id}",
					"protocolProfileBehavior": {
						"disableBodyPruning": true
					},
					"request": {
						"auth": {
							"type": "bearer",
							"bearer": [
								{
									"key": "token",
									"value": "{{token}}",
									"type": "string"
								}
							]
						},
						"method": "GET",
						"header": [],
						"body": {
							"mode": "raw",
							"raw": ""
						},
						"url": {
							"raw": "{{host}}/role-permission/1",
							"host": [
								"{{host}}"
							],
							"path": [
								"role-permission",
								"1"
							]
						}
					},
					"response": []
				},
				{
					"name": "role_permission/getbypermission/{id}",
					"protocolProfileBehavior": {
						"disableBodyPruning": true
					},
					"request": {
						"auth": {
							"type": "bearer",
							"bearer": [
								{
									"key": "token",
									"value": "{{token}}",
									"type": "string"
								}
							]
						},
						"method": "GET",
						"header": [],
						"body": {
							"mode": "raw",
							"raw": ""
						},
						"url": {
							"raw": "{{host}}/role-permission/permission/63",
							"host": [
								"{{host}}"
							],
							"path": [
								"role-permission",
								"permission",
								"63"
							]
						}
					},
					"response": []
				},
				{
					"name": "role_permission/getbyrole/{id}",
					"protocolProfileBehavior": {
						"disableBodyPruning": true
					},
					"request": {
						"auth": {
							"type": "bearer",
							"bearer": [
								{
									"key": "token",
									"value": "{{token}}",
									"type": "string"
								}
							]
						},
						"method": "GET",
						"header": [],
						"body": {
							"mode": "raw",
							"raw": ""
						},
						"url": {
							"raw": "{{host}}/role-permission/role/1",
							"host": [
								"{{host}}"
							],
							"path": [
								"role-permission",
								"role",
								"1"
							]
						}
					},
					"response": []
				}
			],
			"protocolProfileBehavior": {}
		}
	],
	"variable": [
		{
			"id": "dd2dc6c4-0481-4763-94e1-9eddd7eec197",
			"key": "host",
			"value": "",
			"type": "string"
		}
	],
	"protocolProfileBehavior": {}
}